RecognizeService/__init__.py
RecognizeService/__main__.py
RecognizeService/api.py
RecognizeService/collection.py
RecognizeService/const.py
RecognizeService/service.py
RecognizeService/service_v0.py
pih_rcgn-1.2.dist-info/METADATA
pih_rcgn-1.2.dist-info/WHEEL
pih_rcgn-1.2.dist-info/entry_points.txt
pih_rcgn-1.2.dist-info/top_level.txt
pih_rcgn-1.2.dist-info/RECORD
