Metadata-Version: 2.1
Name: pih-rcgn
Version: 1.2
Summary: PIH Recognize service module
Home-page: https://pacifichosp.com/
Author: Nikita Karachentsev
Author-email: it@pacifichosp.com
License: MIT
Requires-Dist: ipih
Requires-Dist: pih-mio
Requires-Dist: pih-tls
